<?xml version="1.0" encoding="utf-8"?>
<odoo>
    <data>

        <record model="perimeter.perimeter" id="perimeter_1">
            <field name="name">Purchasing</field>
        </record>

        <record model="perimeter.perimeter" id="perimeter_2">
            <field name="name">Sales</field>
        </record>

        <record model="perimeter.perimeter" id="perimeter_3">
            <field name="name">Documents</field>
        </record>

        <record model="perimeter.perimeter" id="perimeter_4">
            <field name="name">Projects</field>
        </record>

        <record model="perimeter.perimeter" id="perimeter_5">
            <field name="name">Agriculture</field>
        </record>

    </data>
</odoo>